rf2t_micro/Attention_module.py
rf2t_micro/DistancePredictor.py
rf2t_micro/Embeddings.py
rf2t_micro/InitStrGenerator.py
rf2t_micro/Transformer.py
rf2t_micro/TrunkModel.py
rf2t_micro/__init__.py
rf2t_micro/cli.py
rf2t_micro/parsers.py
rf2t_micro/performer_pytorch.py
rf2t_micro/predict_msa.py
rf2t_micro/resnet.py
rf2t_micro/weights.py
rf2t_micro-0.0.1.post1.dist-info/LICENSE
rf2t_micro-0.0.1.post1.dist-info/METADATA
rf2t_micro-0.0.1.post1.dist-info/WHEEL
rf2t_micro-0.0.1.post1.dist-info/entry_points.txt
rf2t_micro-0.0.1.post1.dist-info/top_level.txt
rf2t_micro-0.0.1.post1.dist-info/RECORD
