Metadata-Version: 2.1
Name: rf2t-micro
Version: 0.0.1.post1
Summary: Stripped-down RosettaFold-2track.
Author-email: Eachan Johnson <eachan.johnson@crick.ac.uk>
License: MIT License
Project-URL: Homepage, https://github.com/scbirlab/sppid
Project-URL: Bug Tracker, https://github.com/scbirlab/sppid/issues
Keywords: science,biology,systems biology,biochemistry,machine learning,analysis,deep learning,rosettafold
Classifier: Development Status :: 3 - Alpha
Classifier: Intended Audience :: Science/Research
Classifier: Topic :: Scientific/Engineering :: Bio-Informatics
Classifier: License :: OSI Approved :: MIT License
Classifier: Programming Language :: Python :: 3.8
Classifier: Programming Language :: Python :: 3.9
Classifier: Programming Language :: Python :: 3.10
Classifier: Programming Language :: Python :: 3.11
Classifier: Programming Language :: Python :: 3 :: Only
Requires-Python: >=3.8
License-File: LICENSE
Requires-Dist: carabiner-tools[mpl]
Requires-Dist: torch
Requires-Dist: torchvision
Requires-Dist: requests
Requires-Dist: tqdm
